{
"skeleton": {
	"hash": "zyquyB9+W64",
	"spine": "4.1.18",
	"x": -489.99,
	"y": 10.77,
	"width": 979.75,
	"height": 425.29,
	"images": "../../../sky2/images/",
	"audio": "C:/Users/User/Desktop/spine__/221204__t/sky2"
},
"bones": [
	{ "name": "root" },
	{ "name": "cloud4-1", "parent": "root", "length": 44.23, "rotation": 1.12, "x": -318.67, "y": 223.01 },
	{ "name": "cloud4-6", "parent": "root", "length": 52.9, "rotation": -0.94, "x": -42.05, "y": 295.85 },
	{ "name": "cloud4-8", "parent": "root", "length": 55.52, "rotation": 1.79, "x": 278.51, "y": 144.02 },
	{ "name": "cloud4-3", "parent": "root", "length": 58.99, "rotation": 1.68, "x": -339.93, "y": 107.6 },
	{ "name": "cloud4-7", "parent": "root", "length": 68.53, "rotation": 1.45, "x": 255.48, "y": 265.02 },
	{ "name": "cloud4-2", "parent": "root", "length": 59.84, "rotation": 0.83, "x": 421.27, "y": 203.18 },
	{ "name": "cloud4-4", "parent": "root", "length": 58.12, "rotation": -1.71, "x": -23.43, "y": 186.47 },
	{ "name": "cloud4-5", "parent": "root", "length": 62.44, "rotation": 0.8, "x": -461.34, "y": 26.05 },
	{ "name": "cloud4-9", "parent": "root", "length": 55.52, "rotation": 1.79, "x": 278.51, "y": 144.02 },
	{ "name": "cloud4-10", "parent": "root", "length": 68.53, "rotation": 1.45, "x": 255.48, "y": 265.02 },
	{ "name": "cloud4-11", "parent": "root", "length": 52.9, "rotation": -0.94, "x": -42.05, "y": 295.85 },
	{ "name": "cloud4-12", "parent": "root", "length": 62.44, "rotation": 0.8, "x": -461.34, "y": 26.05 }
],
"slots": [
	{ "name": "01", "bone": "root", "attachment": "01" },
	{ "name": "cloud4-1", "bone": "cloud4-1", "attachment": "cloud4-1" },
	{ "name": "cloud4-2", "bone": "cloud4-2", "attachment": "cloud4-2" },
	{ "name": "cloud4-3", "bone": "cloud4-3", "attachment": "cloud4-3" },
	{ "name": "cloud4-4", "bone": "cloud4-4", "attachment": "cloud4-4" },
	{ "name": "cloud4-5", "bone": "cloud4-5", "attachment": "cloud4-5" },
	{ "name": "cloud4-12", "bone": "cloud4-12", "attachment": "cloud4-5" },
	{ "name": "cloud4-6", "bone": "cloud4-6", "attachment": "cloud4-6" },
	{ "name": "cloud4-11", "bone": "cloud4-11", "attachment": "cloud4-6" },
	{ "name": "cloud4-7", "bone": "cloud4-7", "attachment": "cloud4-7" },
	{ "name": "cloud4-10", "bone": "cloud4-10", "attachment": "cloud4-7" },
	{ "name": "cloud4-8", "bone": "cloud4-8", "attachment": "cloud4-8" },
	{ "name": "cloud4-9", "bone": "cloud4-9", "attachment": "cloud4-8" }
],
"skins": [
	{
		"name": "default",
		"attachments": {
			"01": {
				"01": {
					"type": "clipping",
					"end": "01",
					"vertexCount": 15,
					"vertices": [ -476.03, 1721.46, -483.79, 1716.41, -490.78, 1705.92, -489.76, 27.66, -485.81, 18.32, -478.63, 12.93, -469.65, 10.77, 473.23, 10.8, 481.85, 15.47, 487.24, 21.93, 489.76, 28.76, 488.14, 1710.68, 483.83, 1717.14, 478.08, 1721.81, 471.98, 1723.61 ],
					"color": "ce3a3aff"
				}
			},
			"cloud4-1": {
				"cloud4-1": {
					"x": 64.03,
					"y": -79.44,
					"scaleX": 4.1559,
					"scaleY": 4.1559,
					"rotation": -1.12,
					"width": 127,
					"height": 65
				}
			},
			"cloud4-2": {
				"cloud4-2": {
					"x": -262.11,
					"y": -118.55,
					"scaleX": 4.1559,
					"scaleY": 4.1559,
					"rotation": -0.83,
					"width": 245,
					"height": 74
				}
			},
			"cloud4-3": {
				"cloud4-3": {
					"x": 414.8,
					"y": -57.97,
					"scaleX": 4.1559,
					"scaleY": 4.1559,
					"rotation": -1.68,
					"width": 264,
					"height": 93
				}
			},
			"cloud4-4": {
				"cloud4-4": {
					"x": -56.8,
					"y": 20.19,
					"scaleX": 4.1559,
					"scaleY": 4.1559,
					"rotation": 1.71,
					"width": 315,
					"height": 95
				}
			},
			"cloud4-5": {
				"cloud4-5": {
					"x": 480.14,
					"y": 61.13,
					"scaleX": 4.1559,
					"scaleY": 4.1559,
					"rotation": -0.8,
					"width": 342,
					"height": 121
				}
			},
			"cloud4-6": {
				"cloud4-6": {
					"x": 140.84,
					"y": -83.21,
					"scaleX": 4.1559,
					"scaleY": 4.1559,
					"rotation": 0.94,
					"width": 239,
					"height": 100
				}
			},
			"cloud4-7": {
				"cloud4-7": {
					"x": -38.94,
					"y": -33.7,
					"scaleX": 4.1559,
					"scaleY": 4.1559,
					"rotation": -1.45,
					"width": 226,
					"height": 99
				}
			},
			"cloud4-8": {
				"cloud4-8": {
					"x": 38.27,
					"y": -116.42,
					"scaleX": 4.1559,
					"scaleY": 4.1559,
					"rotation": -1.79,
					"width": 118,
					"height": 73
				}
			},
			"cloud4-9": {
				"cloud4-8": {
					"x": 38.27,
					"y": -116.42,
					"scaleX": 4.1559,
					"scaleY": 4.1559,
					"rotation": -1.79,
					"width": 118,
					"height": 73
				}
			},
			"cloud4-10": {
				"cloud4-7": {
					"x": -38.94,
					"y": -33.7,
					"scaleX": 4.1559,
					"scaleY": 4.1559,
					"rotation": -1.45,
					"width": 226,
					"height": 99
				}
			},
			"cloud4-11": {
				"cloud4-6": {
					"x": 140.84,
					"y": -83.21,
					"scaleX": 4.1559,
					"scaleY": 4.1559,
					"rotation": 0.94,
					"width": 239,
					"height": 100
				}
			},
			"cloud4-12": {
				"cloud4-5": {
					"x": 480.14,
					"y": 61.13,
					"scaleX": 4.1559,
					"scaleY": 4.1559,
					"rotation": -0.8,
					"width": 342,
					"height": 121
				}
			}
		}
	}
],
"animations": {
	"sky": {
		"slots": {
			"cloud4-1": {
				"rgba": [
					{ "color": "ffffffa9" },
					{ "time": 2.1333, "color": "ffffffff" },
					{ "time": 7.4667, "color": "ffffff00", "curve": "stepped" },
					{ "time": 8.5333, "color": "ffffff00" },
					{ "time": 12.8333, "color": "ffffffa9" }
				]
			},
			"cloud4-2": {
				"rgba": [
					{ "color": "ffffffff" },
					{ "time": 5.3333, "color": "ffffff00", "curve": "stepped" },
					{ "time": 6.4, "color": "ffffff00" },
					{ "time": 12.8333, "color": "ffffffff" }
				]
			},
			"cloud4-3": {
				"rgba": [
					{ "color": "ffffff00", "curve": "stepped" },
					{ "time": 6.6333, "color": "ffffff00" },
					{ "time": 7.4, "color": "ffffffff" },
					{ "time": 12.8333, "color": "ffffff00" }
				]
			},
			"cloud4-4": {
				"rgba": [
					{ "color": "ffffff7f" },
					{ "time": 3.2, "color": "fffffffe" },
					{ "time": 8.5333, "color": "ffffff00", "curve": "stepped" },
					{ "time": 9.6333, "color": "ffffff00" },
					{ "time": 12.8333, "color": "ffffff7f" }
				]
			},
			"cloud4-5": {
				"rgba": [
					{ "color": "ffffff00" },
					{ "time": 6.4, "color": "ffffffff" },
					{ "time": 12.8333, "color": "ffffff00" }
				]
			},
			"cloud4-6": {
				"rgba": [
					{ "color": "ffffff00" },
					{ "time": 2.1333, "color": "ffffffaa", "curve": "stepped" },
					{ "time": 10.7, "color": "ffffffaa" },
					{ "time": 12.8333, "color": "ffffff00" }
				]
			},
			"cloud4-7": {
				"rgba": [
					{ "color": "ffffff00" },
					{ "time": 3.2, "color": "ffffffbe", "curve": "stepped" },
					{ "time": 9.6333, "color": "ffffffbe" },
					{ "time": 12.8333, "color": "ffffff00" }
				]
			},
			"cloud4-8": {
				"rgba": [
					{ "color": "ffffff00" },
					{ "time": 9.6333, "color": "ffffffc8" },
					{ "time": 12.8333, "color": "ffffff00" }
				]
			},
			"cloud4-9": {
				"rgba": [
					{ "color": "ffffff85" },
					{ "time": 2.1333, "color": "ffffff00", "curve": "stepped" },
					{ "time": 4.2667, "color": "ffffff00" },
					{ "time": 11.7667, "color": "ffffffc8" },
					{ "time": 12.8333, "color": "ffffff85" }
				]
			},
			"cloud4-10": {
				"rgba": [
					{ "color": "ffffffbe", "curve": "stepped" },
					{ "time": 2.1333, "color": "ffffffbe" },
					{ "time": 5.3333, "color": "ffffff00", "curve": "stepped" },
					{ "time": 6.4, "color": "ffffff00" },
					{ "time": 9.6333, "color": "ffffffbe" }
				]
			},
			"cloud4-11": {
				"rgba": [
					{ "color": "ffffffaa", "curve": "stepped" },
					{ "time": 3.2, "color": "ffffffaa" },
					{ "time": 5.3333, "color": "ffffff00", "curve": "stepped" },
					{ "time": 6.4, "color": "ffffff00" },
					{ "time": 8.5333, "color": "ffffffaa" }
				]
			},
			"cloud4-12": {
				"rgba": [
					{ "color": "ffffffe5" },
					{ "time": 4.8, "color": "ffffff00", "curve": "stepped" },
					{ "time": 5.8667, "color": "ffffff00" },
					{ "time": 12.3, "color": "ffffffff" },
					{ "time": 12.8333, "color": "ffffffe5" }
				]
			}
		},
		"bones": {
			"cloud4-1": {
				"translate": [
					{ "x": -46.75, "y": -0.92 },
					{ "time": 7.4667 },
					{ "time": 8.5333, "x": -73.46, "y": -1.44 },
					{ "time": 12.8333, "x": -46.75, "y": -0.92 }
				]
			},
			"cloud4-2": {
				"translate": [
					{ "x": -14.41, "y": -0.21 },
					{ "time": 5.3333, "x": 38.79, "y": 0.56 },
					{ "time": 6.4, "x": -78.26, "y": -1.13 },
					{ "time": 12.8333, "x": -14.41, "y": -0.21 }
				]
			},
			"cloud4-3": {
				"translate": [
					{ "x": -50.44, "y": -1.48 },
					{ "time": 6.4, "x": 61.73, "y": 1.82 },
					{ "time": 6.4667, "x": -50.44, "y": -1.48 },
					{ "time": 12.8333, "x": 61.73, "y": 1.82 }
				]
			},
			"cloud4-4": {
				"translate": [
					{ "x": -26.73, "y": 0.8 },
					{ "time": 8.5333, "x": 55.79, "y": -1.67 },
					{ "time": 9.6333, "x": -57.68, "y": 1.72 },
					{ "time": 12.8333, "x": -26.73, "y": 0.8 }
				]
			},
			"cloud4-5": {
				"translate": [
					{},
					{ "time": 12.8333, "x": 61.33, "y": 0.85 }
				]
			},
			"cloud4-6": {
				"translate": [
					{},
					{ "time": 12.8333, "x": 80.07, "y": -1.31 }
				]
			},
			"cloud4-7": {
				"translate": [
					{ "x": -95.43, "y": -2.42 },
					{ "time": 12.8333, "x": 49.74, "y": 1.26 }
				]
			},
			"cloud4-8": {
				"translate": [
					{ "x": -60.88, "y": -1.9 },
					{ "time": 12.8333, "x": 49.46, "y": 1.55 }
				]
			},
			"cloud4-9": {
				"translate": [
					{ "x": 27.39, "y": 0.86 },
					{ "time": 2.1333, "x": 49.46, "y": 1.55 },
					{ "time": 4.2667, "x": -60.88, "y": -1.9 },
					{ "time": 12.8333, "x": 27.39, "y": 0.86 }
				]
			},
			"cloud4-10": {
				"translate": [
					{ "x": -16.25, "y": -0.41 },
					{ "time": 5.3333, "x": 49.74, "y": 1.26 },
					{ "time": 6.4, "x": -95.43, "y": -2.42 },
					{ "time": 12.8333, "x": -16.25, "y": -0.41 }
				]
			},
			"cloud4-11": {
				"translate": [
					{ "x": 43.68, "y": -0.72 },
					{ "time": 5.3333, "x": 80.07, "y": -1.31 },
					{ "time": 6.4 },
					{ "time": 12.8333, "x": 43.68, "y": -0.72 }
				]
			},
			"cloud4-12": {
				"translate": [
					{ "x": 36.24, "y": 0.5 },
					{ "time": 4.8, "x": 61.33, "y": 0.85 },
					{ "time": 5.8667 },
					{ "time": 12.8333, "x": 36.24, "y": 0.5 }
				]
			},
			"root": {
				"translate": [
					{ "y": -857.99 }
				]
			}
		}
	}
}
}